.gitignore
CHANGES.rst
LICENSE.rst
MANIFEST.in
README.rst
bootstrap.py
buildout.cfg
setup.py
syseggrecipe/__init__.py
syseggrecipe/recipe.py
syseggrecipe.egg-info/PKG-INFO
syseggrecipe.egg-info/SOURCES.txt
syseggrecipe.egg-info/dependency_links.txt
syseggrecipe.egg-info/entry_points.txt
syseggrecipe.egg-info/not-zip-safe
syseggrecipe.egg-info/requires.txt
syseggrecipe.egg-info/top_level.txt