Metadata-Version: 1.0
Name: syseggrecipe
Version: 0.4
Summary: Syseggrecipe allows the reuse of system eggs in buildout installs
Home-page: https://github.com/nens/syseggrecipe
Author: Roland van Laar
Author-email: roland@nelen-schuurmans.nl
License: MIT
Platform: UNKNOWN
Classifier: Framework :: Buildout
Classifier: Topic :: Software Development :: Build Tools
Classifier: Development Status :: 4 - Beta
Classifier: License :: OSI Approved :: MIT License
Classifier: Programming Language :: Python :: 2.6
Classifier: Programming Language :: Python :: 2.7
Classifier: Environment :: MacOS X
Classifier: Environment :: Console
